{"metadata": {"dbt_schema_version": "https://schemas.getdbt.com/dbt/sources/v3.json", "dbt_version": "1.10.17", "generated_at": "2026-03-20T09:01:39.020062Z", "invocation_id": "307981fd-e6a4-49be-941d-4a175038b516", "invocation_started_at": "2026-03-20T09:01:10.916916Z", "env": {}}, "results": [{"unique_id": "source.ecommerce_analytics_platform.raw.payments", "max_loaded_at": "2026-03-19T17:39:06.414686+00:00", "snapshotted_at": "2026-03-20T09:01:35.336392+00:00", "max_loaded_at_time_ago_in_s": 55348.921706, "status": "pass", "criteria": {"warn_after": {"count": 24, "period": "hour"}, "error_after": {"count": 48, "period": "hour"}, "filter": null}, "adapter_response": {"_message": "SELECT (1.0 rows, 71.4 KiB processed)", "code": "SELECT", "rows_affected": 1, "bytes_processed": 73112, "bytes_billed": 10485760, "location": "asia-south1", "project_id": "intense-pixel-490219-h2", "job_id": "2d89b69e-8c7c-4b2c-86b4-2ddd07063d9e", "slot_ms": 28}, "timing": [{"name": "compile", "started_at": "2026-03-20T09:01:35.472321Z", "completed_at": "2026-03-20T09:01:35.472321Z"}, {"name": "execute", "started_at": "2026-03-20T09:01:35.573662Z", "completed_at": "2026-03-20T09:01:37.306152Z"}], "thread_id": "Thread-4 (worker)", "execution_time": 1.854111671447754}, {"unique_id": "source.ecommerce_analytics_platform.raw.orders", "max_loaded_at": "2026-03-19T17:38:57.870721+00:00", "snapshotted_at": "2026-03-20T09:01:35.301625+00:00", "max_loaded_at_time_ago_in_s": 55357.430904, "status": "pass", "criteria": {"warn_after": {"count": 24, "period": "hour"}, "error_after": {"count": 48, "period": "hour"}, "filter": null}, "adapter_response": {"_message": "SELECT (1.0 rows, 71.4 KiB processed)", "code": "SELECT", "rows_affected": 1, "bytes_processed": 73112, "bytes_billed": 10485760, "location": "asia-south1", "project_id": "intense-pixel-490219-h2", "job_id": "b736d932-bb7a-4877-a74d-ae46357848a0", "slot_ms": 36}, "timing": [{"name": "compile", "started_at": "2026-03-20T09:01:35.472321Z", "completed_at": "2026-03-20T09:01:35.472321Z"}, {"name": "execute", "started_at": "2026-03-20T09:01:35.563559Z", "completed_at": "2026-03-20T09:01:37.416470Z"}], "thread_id": "Thread-3 (worker)", "execution_time": 1.9644298553466797}, {"unique_id": "source.ecommerce_analytics_platform.raw.order_items", "max_loaded_at": "2026-03-19T17:39:01.083016+00:00", "snapshotted_at": "2026-03-20T09:01:36.728588+00:00", "max_loaded_at_time_ago_in_s": 55355.645572, "status": "pass", "criteria": {"warn_after": {"count": 24, "period": "hour"}, "error_after": {"count": 48, "period": "hour"}, "filter": null}, "adapter_response": {"_message": "SELECT (1.0 rows, 214.5 KiB processed)", "code": "SELECT", "rows_affected": 1, "bytes_processed": 219600, "bytes_billed": 10485760, "location": "asia-south1", "project_id": "intense-pixel-490219-h2", "job_id": "64a573d7-7b9b-4c0c-aede-888d8366d50c", "slot_ms": 21}, "timing": [{"name": "compile", "started_at": "2026-03-20T09:01:35.472321Z", "completed_at": "2026-03-20T09:01:35.472321Z"}, {"name": "execute", "started_at": "2026-03-20T09:01:35.543307Z", "completed_at": "2026-03-20T09:01:38.387961Z"}], "thread_id": "Thread-2 (worker)", "execution_time": 2.935920476913452}, {"unique_id": "source.ecommerce_analytics_platform.raw.customers", "max_loaded_at": "2026-03-19T17:38:50.064540+00:00", "snapshotted_at": "2026-03-20T09:01:36.713287+00:00", "max_loaded_at_time_ago_in_s": 55366.648747, "status": "pass", "criteria": {"warn_after": {"count": 24, "period": "hour"}, "error_after": {"count": 48, "period": "hour"}, "filter": null}, "adapter_response": {"_message": "SELECT (1.0 rows, 14.9 KiB processed)", "code": "SELECT", "rows_affected": 1, "bytes_processed": 15232, "bytes_billed": 10485760, "location": "asia-south1", "project_id": "intense-pixel-490219-h2", "job_id": "5b01f8b9-56f6-403d-b5f1-f6dc330b5124", "slot_ms": 31}, "timing": [{"name": "compile", "started_at": "2026-03-20T09:01:35.470236Z", "completed_at": "2026-03-20T09:01:35.470236Z"}, {"name": "execute", "started_at": "2026-03-20T09:01:35.472321Z", "completed_at": "2026-03-20T09:01:38.550345Z"}], "thread_id": "Thread-1 (worker)", "execution_time": 3.108400821685791}, {"unique_id": "source.ecommerce_analytics_platform.raw.shipments", "max_loaded_at": "2026-03-19T17:39:10.253043+00:00", "snapshotted_at": "2026-03-20T09:01:37.280687+00:00", "max_loaded_at_time_ago_in_s": 55347.027644, "status": "pass", "criteria": {"warn_after": {"count": 24, "period": "hour"}, "error_after": {"count": 48, "period": "hour"}, "filter": null}, "adapter_response": {"_message": "SELECT (1.0 rows, 24.1 KiB processed)", "code": "SELECT", "rows_affected": 1, "bytes_processed": 24648, "bytes_billed": 10485760, "location": "asia-south1", "project_id": "intense-pixel-490219-h2", "job_id": "d76ce0e0-1af0-4175-b964-e315f7977942", "slot_ms": 31}, "timing": [{"name": "compile", "started_at": "2026-03-20T09:01:37.329760Z", "completed_at": "2026-03-20T09:01:37.329760Z"}, {"name": "execute", "started_at": "2026-03-20T09:01:37.331760Z", "completed_at": "2026-03-20T09:01:38.988824Z"}], "thread_id": "Thread-4 (worker)", "execution_time": 1.6640594005584717}], "elapsed_time": 9.66226840019226}